MANIFEST.in
README.md
setup.cfg
setup.py
AWSEnums/__init__.py
AWSEnums/availability_zone.py
AWSEnums/mapper.py
AWSEnums/region.py
AWSEnums.egg-info/PKG-INFO
AWSEnums.egg-info/SOURCES.txt
AWSEnums.egg-info/dependency_links.txt
AWSEnums.egg-info/requires.txt
AWSEnums.egg-info/top_level.txt
AWSEnums/general/__init__.py
AWSEnums/general/currency_code.py
AWSEnums/instance/__init__.py
AWSEnums/instance/platform.py
AWSEnums/instance/tenancy.py
AWSEnums/instance/type.py
AWSEnums/reserved_instance/__init__.py
AWSEnums/reserved_instance/scope.py
AWSEnums/reserved_instance/subscription.py
AWSEnums/reserved_instance/type.py
AWSEnums/reserved_instance/subscription/__init__.py
AWSEnums/reserved_instance/subscription/status.py
AWSEnums/reserved_instance/subscription/type.py